text2qna/__init__.py
text2qna/chunker.py
text2qna/cli.py
text2qna/config.py
text2qna/embeddings.py
text2qna/errors.py
text2qna/policies.py
text2qna/prompts.py
text2qna/py.typed
text2qna/qna.py
text2qna/types.py
text2qna/utils.py
text2qna-0.1.2.dist-info/licenses/LICENSE
text2qna-0.1.2.dist-info/METADATA
text2qna-0.1.2.dist-info/WHEEL
text2qna-0.1.2.dist-info/entry_points.txt
text2qna-0.1.2.dist-info/top_level.txt
text2qna-0.1.2.dist-info/RECORD
