Metadata-Version: 2.4
Name: text2qna
Version: 0.1.2
Summary: Command-line tool to split documents into chunks and automatically generate question–answer datasets, designed for preparing data to fine-tune large language models (LLMs).
Author: Nikolaos Giovanopoulos
License: MIT License
Project-URL: Homepage, https://github.com/nikosgiov/text2qna
Project-URL: Repository, https://github.com/nikosgiov/text2qna
Project-URL: Issues, https://github.com/nikosgiov/text2qna/issues
Project-URL: Changelog, https://github.com/nikosgiov/text2qna/releases
Keywords: qna,chunking,embeddings,llm,markdown,dataset
Classifier: License :: OSI Approved :: MIT License
Classifier: Environment :: Console
Classifier: Programming Language :: Python :: 3
Classifier: Programming Language :: Python :: 3.9
Classifier: Programming Language :: Python :: 3.10
Classifier: Programming Language :: Python :: 3.11
Classifier: Programming Language :: Python :: 3.12
Classifier: Operating System :: OS Independent
Classifier: Typing :: Typed
Requires-Python: >=3.9
License-File: LICENSE
Requires-Dist: openai>=1.95.1
Requires-Dist: markdown>=3.8.2
Requires-Dist: beautifulsoup4>=4.13.4
Requires-Dist: markdownify>=1.2.0
Requires-Dist: requests>=2.32.4
Requires-Dist: numpy<2.0; python_version < "3.10"
Requires-Dist: numpy<2.3,>=2.0; python_version >= "3.10" and python_version < "3.11"
Requires-Dist: numpy>=2.3; python_version >= "3.11"
Requires-Dist: scikit-learn<1.7,>=1.6.1; python_version < "3.10"
Requires-Dist: scikit-learn>=1.7.2; python_version >= "3.10"
Provides-Extra: pdf
Requires-Dist: pdfplumber>=0.11.7; extra == "pdf"
Provides-Extra: local
Requires-Dist: sentence-transformers>=5.1.0; extra == "local"
Provides-Extra: nltk
Requires-Dist: nltk>=3.9.1; extra == "nltk"
Dynamic: license-file
